Suschtsch/__init__.py
Suschtsch/sub_classes.py
Suschtsch/suschtsch.py
suschtsch-0.0.1.dist-info/METADATA
suschtsch-0.0.1.dist-info/WHEEL
suschtsch-0.0.1.dist-info/top_level.txt
suschtsch-0.0.1.dist-info/RECORD
