Metadata-Version: 2.1
Name: suschtsch
Version: 0.0.1
Summary: Just suschtsch it!
Home-page: https://github.com/IAmSerepok/suschtsch
Author: Serepok
Author-email: gromyko-04@bk.ru
Project-URL: GitHub, https://github.com/IAmSerepok/suschtsch
Keywords: suschtsch shit
Classifier: Programming Language :: Python :: 3.11
Classifier: License :: OSI Approved :: MIT License
Classifier: Operating System :: OS Independent
Requires-Python: >=3.6
Requires-Dist: requests >=2.25.1
